Metadata-Version: 2.1
Name: sqlite-utils-fast-fks
Version: 0.1
Summary: Fast foreign key addition for sqlite-utils
Author: Simon Willison
License: Apache-2.0
Project-URL: Homepage, https://github.com/simonw/sqlite-utils-fast-fks
Project-URL: Changelog, https://github.com/simonw/sqlite-utils-fast-fks/releases
Project-URL: Issues, https://github.com/simonw/sqlite-utils-fast-fks/issues
Project-URL: CI, https://github.com/simonw/sqlite-utils-fast-fks/actions
Classifier: License :: OSI Approved :: Apache Software License
Requires-Dist: sqlite-utils
Provides-Extra: test
Requires-Dist: pytest ; extra == 'test'
